nlpkwords/__init__.py
nlpkwords/a_dir_csv.py
nlpkwords/a_dir_user.py
nlpkwords/a_undir_csv.py
nlpkwords/a_undir_user.py
nlpkwords/best_fs_directed.py
nlpkwords/best_fs_undirect_unweight.py
nlpkwords/best_fs_undirected.py
nlpkwords/bfs.py
nlpkwords/bfs_dir_weight.py
nlpkwords/bow.py
nlpkwords/dfs_non_recursive.py
nlpkwords/dfs_recursive.py
nlpkwords/fuzzy_3set.py
nlpkwords/fuzzy_coi.py
nlpkwords/fuzzy_cou.py
nlpkwords/lemmatization.py
nlpkwords/nim_game_loses.py
nlpkwords/nim_win.py
nlpkwords/onehot.py
nlpkwords/relu.py
nlpkwords/sigmoid.py
nlpkwords/simple_mlp.py
nlpkwords/tanh.py
nlpkwords/tf_idf.py
nlpkwords/tokenization.py
nlpkwords-0.1.0.dist-info/licenses/LICENSE
nlpkwords-0.1.0.dist-info/METADATA
nlpkwords-0.1.0.dist-info/WHEEL
nlpkwords-0.1.0.dist-info/top_level.txt
nlpkwords-0.1.0.dist-info/RECORD
