Metadata-Version: 2.4
Name: nlpkwords
Version: 0.1.0
Summary: A package containing AI/ML codes
Home-page: https://github.com/nOTpROGRAMMERr/nlpkwords
Author: Rish Dias
Author-email: rishrdias672004@gmail.com
Keywords: nlp,machine learning,artificial intelligence,education
Classifier: Development Status :: 3 - Alpha
Classifier: Intended Audience :: Education
Classifier: License :: OSI Approved :: MIT License
Classifier: Programming Language :: Python :: 3
Classifier: Programming Language :: Python :: 3.6
Classifier: Programming Language :: Python :: 3.7
Classifier: Programming Language :: Python :: 3.8
Classifier: Programming Language :: Python :: 3.9
Classifier: Programming Language :: Python :: 3.10
Requires-Python: >=3.6
License-File: LICENSE
Requires-Dist: pandas>=1.3.0
Requires-Dist: nltk>=3.6.0
Requires-Dist: textblob>=0.15.3
Requires-Dist: scikit-learn>=0.24.0
Requires-Dist: numpy>=1.20.0
Dynamic: author
Dynamic: author-email
Dynamic: classifier
Dynamic: description
Dynamic: description-content-type
Dynamic: home-page
Dynamic: keywords
Dynamic: license-file
Dynamic: requires-dist
Dynamic: requires-python
Dynamic: summary
